Commacceslib/__init__.py
Commacceslib/comm.py
Commacceslib/use_comm.py
Commacceslib/data_convert/__init__.py
Commacceslib/data_convert/chip_bitmap_pos.py
Commacceslib/data_convert/data_swap.py
Commacceslib-0.0.5.dist-info/METADATA
Commacceslib-0.0.5.dist-info/WHEEL
Commacceslib-0.0.5.dist-info/top_level.txt
Commacceslib-0.0.5.dist-info/RECORD
