Metadata-Version: 2.1
Name: Commacceslib
Version: 0.0.5
Summary: This lib controls library fro ProbeCard project
Home-page: UNKNOWN
License: CC0 1.0 Universal
Platform: UNKNOWN
Classifier: Development Status :: 4 - Beta
Classifier: Programming Language :: Python :: 3
Requires-Python: >=3
Requires-Dist: numpy (==1.22.3)
